MANIFEST.in
README.md
requirements.txt
setup.py
compiler/__init__.py
compiler/api/__init__.py
compiler/api/compiler.py
compiler/api/source/auth_key.tl
compiler/api/source/main_api.tl
compiler/api/source/sys_msgs.tl
compiler/api/template/combinator.txt
compiler/api/template/type.txt
compiler/errors/__init__.py
compiler/errors/compiler.py
compiler/errors/sort.py
compiler/errors/source/303_SEE_OTHER.tsv
compiler/errors/source/400_BAD_REQUEST.tsv
compiler/errors/source/401_UNAUTHORIZED.tsv
compiler/errors/source/403_FORBIDDEN.tsv
compiler/errors/source/406_NOT_ACCEPTABLE.tsv
compiler/errors/source/420_FLOOD.tsv
compiler/errors/source/500_INTERNAL_SERVER_ERROR.tsv
compiler/errors/source/503_SERVICE_UNAVAILABLE.tsv
compiler/errors/template/class.txt
compiler/errors/template/sub_class.txt
haku/__init__.py
haku/client.py
haku/dispatcher.py
haku/emoji.py
haku/file_id.py
haku/filters.py
haku/mime_types.py
haku/py.typed
haku/sync.py
haku/utils.py
haku.egg-info/PKG-INFO
haku.egg-info/SOURCES.txt
haku.egg-info/dependency_links.txt
haku.egg-info/requires.txt
haku.egg-info/top_level.txt
haku/connection/__init__.py
haku/connection/connection.py
haku/connection/transport/__init__.py
haku/connection/transport/tcp/__init__.py
haku/connection/transport/tcp/tcp.py
haku/connection/transport/tcp/tcp_abridged.py
haku/connection/transport/tcp/tcp_abridged_o.py
haku/connection/transport/tcp/tcp_full.py
haku/connection/transport/tcp/tcp_intermediate.py
haku/connection/transport/tcp/tcp_intermediate_o.py
haku/crypto/__init__.py
haku/crypto/aes.py
haku/crypto/mtproto.py
haku/crypto/prime.py
haku/crypto/rsa.py
haku/enums/__init__.py
haku/enums/auto_name.py
haku/enums/business_schedule.py
haku/enums/chat_action.py
haku/enums/chat_event_action.py
haku/enums/chat_member_status.py
haku/enums/chat_members_filter.py
haku/enums/chat_type.py
haku/enums/listerner_types.py
haku/enums/message_entity_type.py
haku/enums/message_media_type.py
haku/enums/message_service_type.py
haku/enums/messages_filter.py
haku/enums/next_code_type.py
haku/enums/parse_mode.py
haku/enums/poll_type.py
haku/enums/profile_color.py
haku/enums/reaction_type.py
